multitools_bag/config.cp37-win_amd64.pyd
multitools_bag/config.cpython-37m-x86_64-linux-gnu.so
multitools_bag/log.cp37-win_amd64.pyd
multitools_bag/log.cpython-37m-x86_64-linux-gnu.so
multitools_bag/regEdit.cp37-win_amd64.pyd
multitools_bag/regEdit.cpython-37m-x86_64-linux-gnu.so
multitools_bag/sqliteConn.cp39-win_amd64.pyd
multitools_bag/sqliteConn.cpython-37m-x86_64-linux-gnu.so
multitools_bag/widgetlog.cp39-win_amd64.pyd
multitools_bag-0.3.5.dist-info/METADATA
multitools_bag-0.3.5.dist-info/WHEEL
multitools_bag-0.3.5.dist-info/top_level.txt
multitools_bag-0.3.5.dist-info/RECORD
