Metadata-Version: 2.1
Name: multitools_bag
Version: 0.3.5
Summary: Multitools: log, config, serial, regedit, etc.
Author: hubosoft
Author-email: hubosoft@hotmail.com
Classifier: Programming Language :: Python :: 3
Classifier: License :: OSI Approved :: MIT License
Classifier: Operating System :: OS Independent
Requires-Python: >=3.6
Requires-Dist: ruamel.yaml
